mse_lib_sgx/__init__.py
mse_lib_sgx/base64url.py
mse_lib_sgx/certificate.py
mse_lib_sgx/cli.py
mse_lib_sgx/copy.py
mse_lib_sgx/error.py
mse_lib_sgx/globs.py
mse_lib_sgx/http_server.py
mse_lib_sgx/py.typed
mse_lib_sgx/sgx/__init__.py
mse_lib_sgx/sgx/key.py
mse_lib_sgx/sgx/quote.py
mse_lib_sgx-2.3.0.dist-info/METADATA
mse_lib_sgx-2.3.0.dist-info/WHEEL
mse_lib_sgx-2.3.0.dist-info/entry_points.txt
mse_lib_sgx-2.3.0.dist-info/top_level.txt
mse_lib_sgx-2.3.0.dist-info/RECORD
